rmq_handler/configuration/__init__.py
rmq_handler/configuration/config.py
rmq_handler/handlers/__init__.py
rmq_handler/handlers/channel.py
rmq_handler/handlers/publisher.py
rmq_handler-0.1.0.dist-info/WHEEL
rmq_handler-0.1.0.dist-info/METADATA
rmq_handler-0.1.0.dist-info/RECORD
