Metadata-Version: 2.1
Name: rmq-handler
Version: 0.1.0
Summary: RabbitMQ connections handler.
Author: Kirill
Author-email: pnchkirill@gmail.com
Requires-Python: >=3.10,<4.0
Classifier: Programming Language :: Python :: 3
Classifier: Programming Language :: Python :: 3.10
Classifier: Programming Language :: Python :: 3.11
Requires-Dist: aio-pika (>=9.3.1,<10.0.0)
